[{"ts": "2021-08-17T07:04:27.915222", "to": "love@q3mcco35auwcstmt.onion", "from": "elvira@q3mcco35auwcstmt.onion", "body": "hi, i wrote. Only I myself am still new since June, how can I help ...."}, {"ts": "2021-08-17T08:11:31.896777", "to": "globus@q3mcco35auwcstmt.onion", "from": "baget@q3mcco35auwcstmt.onion", "body": "Hello."}, {"ts": "2021-08-17T08:31:56.090774", "to": "vampire@q3mcco35auwcstmt.onion", "from": "mango@q3mcco35auwcstmt.onion", "body": "hi bro come on ladies sn"}, {"ts": "2021-08-17T10:53:34.294215", "to": "hors@q3mcco35auwcstmt.onion", "from": "pin@q3mcco35auwcstmt.onion", "body": "Hey"}, {"ts": "2021-08-17T10:53:38.179086", "to": "hors@q3mcco35auwcstmt.onion", "from": "pin@q3mcco35auwcstmt.onion", "body": "was it not?"}, {"ts": "2021-08-17T11:01:01.325186", "to": "hors@q3mcco35auwcstmt.onion", "from": "elvira@q3mcco35auwcstmt.onion", "body": "Hello , please come to your place there in the rocket a couple of people are waiting online now"}, {"ts": "2021-08-17T11:04:02.200376", "to": "defender@q3mcco35auwcstmt.onion", "from": "driver@q3mcco35auwcstmt.onion", "body": "Error: The message is encrypted and cannot be decrypted.]"}, {"ts": "2021-08-17T11:06:33.913579", "to": "driver@q3mcco35auwcstmt.onion", "from": "defender@q3mcco35auwcstmt.onion", "body": "Error: The message is encrypted and cannot be decrypted.]"}, {"ts": "2021-08-17T11:06:47.015123", "to": "driver@q3mcco35auwcstmt.onion", "from": "defender@q3mcco35auwcstmt.onion", "body": "Error: The message is encrypted and cannot be decrypted.]"}, {"ts": "2021-08-17T11:06:56.499069", "to": "driver@q3mcco35auwcstmt.onion", "from": "defender@q3mcco35auwcstmt.onion", "body": "Error: The message is encrypted and cannot be decrypted.]"}, {"ts": "2021-08-17T11:10:13.944810", "to": "defender@q3mcco35auwcstmt.onion", "from": "driver@q3mcco35auwcstmt.onion", "body": "Error: The message is encrypted and cannot be decrypted.]"}, {"ts": "2021-08-17T11:27:39.895152", "to": "driver@q3mcco35auwcstmt.onion", "from": "defender@q3mcco35auwcstmt.onion", "body": "Error: The message is encrypted and cannot be decrypted.]"}, {"ts": "2021-08-17T11:30:22.220758", "to": "driver@q3mcco35auwcstmt.onion", "from": "defender@q3mcco35auwcstmt.onion", "body": "Error: The message is encrypted and cannot be decrypted.]"}, {"ts": "2021-08-17T11:31:40.955002", "to": "driver@q3mcco35auwcstmt.onion", "from": "defender@q3mcco35auwcstmt.onion", "body": "Error: The message is encrypted and cannot be decrypted.]"}, {"ts": "2021-08-17T11:31:45.107121", "to": "defender@q3mcco35auwcstmt.onion", "from": "driver@q3mcco35auwcstmt.onion", "body": "Error: The message is encrypted and cannot be decrypted.]"}, {"ts": "2021-08-17T11:32:14.815697", "to": "driver@q3mcco35auwcstmt.onion", "from": "defender@q3mcco35auwcstmt.onion", "body": "Error: The message is encrypted and cannot be decrypted.]"}, {"ts": "2021-08-17T11:35:28.906657", "to": "professor@q3mcco35auwcstmt.onion", "from": "batka@q3mcco35auwcstmt.onion", "body": "hey, any news?"}, {"ts": "2021-08-17T11:44:35.277410", "to": "hof@q3mcco35auwcstmt.onion", "from": "defender@q3mcco35auwcstmt.onion", "body": "Error: The message is encrypted and cannot be decrypted.]"}, {"ts": "2021-08-17T11:45:00.410357", "to": "defender@q3mcco35auwcstmt.onion", "from": "hof@q3mcco35auwcstmt.onion", "body": "Error: The message is encrypted and cannot be decrypted.]"}, {"ts": "2021-08-17T11:45:36.911493", "to": "hof@q3mcco35auwcstmt.onion", "from": "defender@q3mcco35auwcstmt.onion", "body": "Error: The message is encrypted and cannot be decrypted.]"}, {"ts": "2021-08-17T11:45:47.623574", "to": "defender@q3mcco35auwcstmt.onion", "from": "hof@q3mcco35auwcstmt.onion", "body": "Error: The message is encrypted and cannot be decrypted.]"}, {"ts": "2021-08-17T11:45:50.242251", "to": "hof@q3mcco35auwcstmt.onion", "from": "defender@q3mcco35auwcstmt.onion", "body": "Error: The message is encrypted and cannot be decrypted.]"}, {"ts": "2021-08-17T11:46:05.596660", "to": "defender@q3mcco35auwcstmt.onion", "from": "hof@q3mcco35auwcstmt.onion", "body": "Error: The message is encrypted and cannot be decrypted.]"}, {"ts": "2021-08-17T11:46:16.019356", "to": "hof@q3mcco35auwcstmt.onion", "from": "defender@q3mcco35auwcstmt.onion", "body": "Error: The message is encrypted and cannot be decrypted.]"}, {"ts": "2021-08-17T11:46:35.543432", "to": "defender@q3mcco35auwcstmt.onion", "from": "hof@q3mcco35auwcstmt.onion", "body": "Error: The message is encrypted and cannot be decrypted.]"}, {"ts": "2021-08-17T11:51:22.318331", "to": "driver@q3mcco35auwcstmt.onion", "from": "defender@q3mcco35auwcstmt.onion", "body": "Error: The message is encrypted and cannot be decrypted.]"}, {"ts": "2021-08-17T11:51:27.185923", "to": "driver@q3mcco35auwcstmt.onion", "from": "defender@q3mcco35auwcstmt.onion", "body": "Error: The message is encrypted and cannot be decrypted.]"}, {"ts": "2021-08-17T11:52:01.275303", "to": "driver@q3mcco35auwcstmt.onion", "from": "defender@q3mcco35auwcstmt.onion", "body": "Error: The message is encrypted and cannot be decrypted.]"}, {"ts": "2021-08-17T11:52:24.267949", "to": "defender@q3mcco35auwcstmt.onion", "from": "driver@q3mcco35auwcstmt.onion", "body": "Error: The message is encrypted and cannot be decrypted.]"}, {"ts": "2021-08-17T11:56:08.969528", "to": "driver@q3mcco35auwcstmt.onion", "from": "defender@q3mcco35auwcstmt.onion", "body": "Error: The message is encrypted and cannot be decrypted.]"}, {"ts": "2021-08-17T11:57:01.430413", "to": "defender@q3mcco35auwcstmt.onion", "from": "driver@q3mcco35auwcstmt.onion", "body": "Error: The message is encrypted and cannot be decrypted.]"}, {"ts": "2021-08-17T11:57:13.220948", "to": "driver@q3mcco35auwcstmt.onion", "from": "defender@q3mcco35auwcstmt.onion", "body": "Error: The message is encrypted and cannot be decrypted.]"}, {"ts": "2021-08-17T11:57:18.153924", "to": "defender@q3mcco35auwcstmt.onion", "from": "driver@q3mcco35auwcstmt.onion", "body": "Error: The message is encrypted and cannot be decrypted.]"}, {"ts": "2021-08-17T11:57:24.565329", "to": "driver@q3mcco35auwcstmt.onion", "from": "defender@q3mcco35auwcstmt.onion", "body": "Error: The message is encrypted and cannot be decrypted.]"}, {"ts": "2021-08-17T11:57:29.860721", "to": "defender@q3mcco35auwcstmt.onion", "from": "driver@q3mcco35auwcstmt.onion", "body": "Error: The message is encrypted and cannot be decrypted.]"}, {"ts": "2021-08-17T11:57:36.443169", "to": "driver@q3mcco35auwcstmt.onion", "from": "defender@q3mcco35auwcstmt.onion", "body": "Error: The message is encrypted and cannot be decrypted.]"}, {"ts": "2021-08-17T11:57:56.383586", "to": "driver@q3mcco35auwcstmt.onion", "from": "defender@q3mcco35auwcstmt.onion", "body": "Error: The message is encrypted and cannot be decrypted.]"}, {"ts": "2021-08-17T11:58:49.220803", "to": "defender@q3mcco35auwcstmt.onion", "from": "driver@q3mcco35auwcstmt.onion", "body": "Error: The message is encrypted and cannot be decrypted.]"}, {"ts": "2021-08-17T11:59:27.529891", "to": "driver@q3mcco35auwcstmt.onion", "from": "defender@q3mcco35auwcstmt.onion", "body": "Error: The message is encrypted and cannot be decrypted.]"}, {"ts": "2021-08-17T11:59:40.232880", "to": "defender@q3mcco35auwcstmt.onion", "from": "driver@q3mcco35auwcstmt.onion", "body": "Error: The message is encrypted and cannot be decrypted.]"}, {"ts": "2021-08-17T11:59:51.236215", "to": "driver@q3mcco35auwcstmt.onion", "from": "defender@q3mcco35auwcstmt.onion", "body": "Error: The message is encrypted and cannot be decrypted.]"}, {"ts": "2021-08-17T12:00:35.509916", "to": "defender@q3mcco35auwcstmt.onion", "from": "driver@q3mcco35auwcstmt.onion", "body": "Error: The message is encrypted and cannot be decrypted.]"}, {"ts": "2021-08-17T12:00:36.583728", "to": "driver@q3mcco35auwcstmt.onion", "from": "defender@q3mcco35auwcstmt.onion", "body": "Error: The message is encrypted and cannot be decrypted.]"}, {"ts": "2021-08-17T12:00:47.364650", "to": "defender@q3mcco35auwcstmt.onion", "from": "driver@q3mcco35auwcstmt.onion", "body": "Error: The message is encrypted and cannot be decrypted.]"}, {"ts": "2021-08-17T12:00:51.919779", "to": "driver@q3mcco35auwcstmt.onion", "from": "defender@q3mcco35auwcstmt.onion", "body": "Error: The message is encrypted and cannot be decrypted.]"}, {"ts": "2021-08-17T12:01:03.635290", "to": "defender@q3mcco35auwcstmt.onion", "from": "driver@q3mcco35auwcstmt.onion", "body": "Error: The message is encrypted and cannot be decrypted.]"}, {"ts": "2021-08-17T12:01:05.307466", "to": "driver@q3mcco35auwcstmt.onion", "from": "defender@q3mcco35auwcstmt.onion", "body": "Error: The message is encrypted and cannot be decrypted.]"}, {"ts": "2021-08-17T12:01:43.285774", "to": "defender@q3mcco35auwcstmt.onion", "from": "driver@q3mcco35auwcstmt.onion", "body": "Error: The message is encrypted and cannot be decrypted.]"}, {"ts": "2021-08-17T12:02:07.768908", "to": "hof@q3mcco35auwcstmt.onion", "from": "defender@q3mcco35auwcstmt.onion", "body": "Error: The message is encrypted and cannot be decrypted.]"}, {"ts": "2021-08-17T12:02:36.524891", "to": "defender@q3mcco35auwcstmt.onion", "from": "hof@q3mcco35auwcstmt.onion", "body": "Error: The message is encrypted and cannot be decrypted.]"}, {"ts": "2021-08-17T12:02:59.853455", "to": "driver@q3mcco35auwcstmt.onion", "from": "defender@q3mcco35auwcstmt.onion", "body": "Error: The message is encrypted and cannot be decrypted.]"}, {"ts": "2021-08-17T12:03:57.819720", "to": "defender@q3mcco35auwcstmt.onion", "from": "driver@q3mcco35auwcstmt.onion", "body": "Error: The message is encrypted and cannot be decrypted.]"}, {"ts": "2021-08-17T12:06:14.554672", "to": "strix@q3mcco35auwcstmt.onion", "from": "hors@q3mcco35auwcstmt.onion", "body": "hello vpny ended, get in touch please"}, {"ts": "2021-08-17T12:06:26.373229", "to": "defender@q3mcco35auwcstmt.onion", "from": "driver@q3mcco35auwcstmt.onion", "body": "Error: The message is encrypted and cannot be decrypted.]"}, {"ts": "2021-08-17T12:14:49.889895", "to": "hors@q3mcco35auwcstmt.onion", "from": "strix@q3mcco35auwcstmt.onion", "body": "hello vpny ended, get in touch please"}, {"ts": "2021-08-17T12:16:18.859053", "to": "driver@q3mcco35auwcstmt.onion", "from": "defender@q3mcco35auwcstmt.onion", "body": "Error: The message is encrypted and cannot be decrypted.]"}, {"ts": "2021-08-17T12:16:49.531025", "to": "defender@q3mcco35auwcstmt.onion", "from": "driver@q3mcco35auwcstmt.onion", "body": "Error: The message is encrypted and cannot be decrypted.]"}, {"ts": "2021-08-17T12:17:41.614228", "to": "hof@q3mcco35auwcstmt.onion", "from": "defender@q3mcco35auwcstmt.onion", "body": "Error: The message is encrypted and cannot be decrypted.]"}, {"ts": "2021-08-17T12:17:57.428271", "to": "hof@q3mcco35auwcstmt.onion", "from": "defender@q3mcco35auwcstmt.onion", "body": "Error: The message is encrypted and cannot be decrypted.]"}, {"ts": "2021-08-17T12:18:03.959710", "to": "hof@q3mcco35auwcstmt.onion", "from": "defender@q3mcco35auwcstmt.onion", "body": "Error: The message is encrypted and cannot be decrypted.]"}, {"ts": "2021-08-17T12:18:32.405854", "to": "defender@q3mcco35auwcstmt.onion", "from": "hof@q3mcco35auwcstmt.onion", "body": "Error: The message is encrypted and cannot be decrypted.]"}, {"ts": "2021-08-17T12:18:47.726303", "to": "hof@q3mcco35auwcstmt.onion", "from": "defender@q3mcco35auwcstmt.onion", "body": "Error: The message is encrypted and cannot be decrypted.]"}, {"ts": "2021-08-17T12:19:12.608132", "to": "driver@q3mcco35auwcstmt.onion", "from": "defender@q3mcco35auwcstmt.onion", "body": "Error: The message is encrypted and cannot be decrypted.]"}, {"ts": "2021-08-17T12:19:36.630734", "to": "defender@q3mcco35auwcstmt.onion", "from": "hof@q3mcco35auwcstmt.onion", "body": "Error: The message is encrypted and cannot be decrypted.]"}, {"ts": "2021-08-17T12:20:53.103315", "to": "defender@q3mcco35auwcstmt.onion", "from": "hof@q3mcco35auwcstmt.onion", "body": "Error: The message is encrypted and cannot be decrypted.]"}, {"ts": "2021-08-17T12:21:04.928220", "to": "hof@q3mcco35auwcstmt.onion", "from": "defender@q3mcco35auwcstmt.onion", "body": "Error: The message is encrypted and cannot be decrypted.]"}, {"ts": "2021-08-17T12:21:46.680142", "to": "defender@q3mcco35auwcstmt.onion", "from": "hof@q3mcco35auwcstmt.onion", "body": "Error: The message is encrypted and cannot be decrypted.]"}, {"ts": "2021-08-17T12:21:53.257120", "to": "defender@q3mcco35auwcstmt.onion", "from": "hof@q3mcco35auwcstmt.onion", "body": "Error: The message is encrypted and cannot be decrypted.]"}, {"ts": "2021-08-17T12:22:37.911817", "to": "hof@q3mcco35auwcstmt.onion", "from": "defender@q3mcco35auwcstmt.onion", "body": "Error: The message is encrypted and cannot be decrypted.]"}, {"ts": "2021-08-17T12:23:46.017966", "to": "defender@q3mcco35auwcstmt.onion", "from": "hof@q3mcco35auwcstmt.onion", "body": "Error: The message is encrypted and cannot be decrypted.]"}, {"ts": "2021-08-17T12:23:51.960342", "to": "defender@q3mcco35auwcstmt.onion", "from": "hof@q3mcco35auwcstmt.onion", "body": "Error: The message is encrypted and cannot be decrypted.]"}, {"ts": "2021-08-17T12:25:00.836592", "to": "defender@q3mcco35auwcstmt.onion", "from": "hof@q3mcco35auwcstmt.onion", "body": "Error: The message is encrypted and cannot be decrypted.]"}, {"ts": "2021-08-17T12:27:15.462785", "to": "stern@q3mcco35auwcstmt.onion", "from": "dominik@q3mcco35auwcstmt.onion", "body": "will you throw off?"}, {"ts": "2021-08-17T12:27:15.467564", "to": "stern@q3mcco35auwcstmt.onion", "from": "mango@q3mcco35auwcstmt.onion", "body": "received, went to distribute"}, {"ts": "2021-08-17T12:27:15.473169", "to": "stern@q3mcco35auwcstmt.onion", "from": "gold@q3mcco35auwcstmt.onion", "body": "https://privnote.com/t8bQ7i7m#tKkPU6mTV"}, {"ts": "2021-08-17T12:27:15.475626", "to": "stern@q3mcco35auwcstmt.onion", "from": "salamandra@q3mcco35auwcstmt.onion", "body": "I&#39;ll take a break and come back with renewed vigor"}, {"ts": "2021-08-17T12:27:15.478096", "to": "stern@q3mcco35auwcstmt.onion", "from": "salamandra@q3mcco35auwcstmt.onion", "body": "two weeks ok?"}, {"ts": "2021-08-17T12:27:15.480806", "to": "stern@q3mcco35auwcstmt.onion", "from": "salamandra@q3mcco35auwcstmt.onion", "body": "bc1qc6fpzh8jkuy7l8nk44yx3dztz36ejwgkq8p5vf"}, {"ts": "2021-08-17T12:27:15.482143", "to": "stern@q3mcco35auwcstmt.onion", "from": "salamandra@q3mcco35auwcstmt.onion", "body": "I would still like to talk, I still don’t understand, are you firing me or letting me rest? forms removed me from the new hunting rocket"}, {"ts": "2021-08-17T12:27:15.486083", "to": "stern@q3mcco35auwcstmt.onion", "from": "dominik@q3mcco35auwcstmt.onion", "body": "bro, we urgently need wells statements for half a year"}, {"ts": "2021-08-17T12:27:15.487390", "to": "stern@q3mcco35auwcstmt.onion", "from": "mango@q3mcco35auwcstmt.onion", "body": "gave a couple of fortiks to the dilon, but as I understand it, he had not worked with them before .."}, {"ts": "2021-08-17T12:27:15.488268", "to": "stern@q3mcco35auwcstmt.onion", "from": "mango@q3mcco35auwcstmt.onion", "body": "zp distributed most of it 33k left, tomorrow I&#39;ll catch the rest"}, {"ts": "2021-08-17T12:28:11.330485", "to": "salamandra@q3mcco35auwcstmt.onion", "from": "stern@q3mcco35auwcstmt.onion", "body": "yes, you can rest for now and come back with renewed vigor, prove here to everyone what you are capable of"}, {"ts": "2021-08-17T12:31:38.904161", "to": "gold@q3mcco35auwcstmt.onion", "from": "stern@q3mcco35auwcstmt.onion", "body": "yeah got it"}, {"ts": "2021-08-17T12:31:41.063184", "to": "gold@q3mcco35auwcstmt.onion", "from": "stern@q3mcco35auwcstmt.onion", "body": "Great"}, {"ts": "2021-08-17T12:35:00.447447", "to": "defender@q3mcco35auwcstmt.onion", "from": "dominik@q3mcco35auwcstmt.onion", "body": "chair of the United States"}, {"ts": "2021-08-17T12:35:10.269595", "to": "dominik@q3mcco35auwcstmt.onion", "from": "defender@q3mcco35auwcstmt.onion", "body": "Washington"}, {"ts": "2021-08-17T12:35:11.384211", "to": "defender@q3mcco35auwcstmt.onion", "from": "dominik@q3mcco35auwcstmt.onion", "body": "chair of the United States"}, {"ts": "2021-08-17T12:35:26.939372", "to": "dominik@q3mcco35auwcstmt.onion", "from": "defender@q3mcco35auwcstmt.onion", "body": "Hey"}, {"ts": "2021-08-17T12:39:40.359373", "to": "defender@q3mcco35auwcstmt.onion", "from": "dominik@q3mcco35auwcstmt.onion", "body": "ku"}, {"ts": "2021-08-17T12:39:49.146932", "to": "zolotoy@q3mcco35auwcstmt.onion", "from": "stern@q3mcco35auwcstmt.onion", "body": "gm@ is gone"}, {"ts": "2021-08-17T12:40:01.140493", "to": "dominik@q3mcco35auwcstmt.onion", "from": "defender@q3mcco35auwcstmt.onion", "body": "to her"}, {"ts": "2021-08-17T12:40:01.752370", "to": "dominik@q3mcco35auwcstmt.onion", "from": "defender@q3mcco35auwcstmt.onion", "body": "Hey"}, {"ts": "2021-08-17T12:40:07.858086", "to": "defender@q3mcco35auwcstmt.onion", "from": "dominik@q3mcco35auwcstmt.onion", "body": "authorize"}, {"ts": "2021-08-17T12:41:32.942555", "to": "driver@q3mcco35auwcstmt.onion", "from": "defender@q3mcco35auwcstmt.onion", "body": "Error: The message is encrypted and cannot be decrypted.]"}, {"ts": "2021-08-17T12:42:08.984793", "to": "defender@q3mcco35auwcstmt.onion", "from": "driver@q3mcco35auwcstmt.onion", "body": "Error: The message is encrypted and cannot be decrypted.]"}, {"ts": "2021-08-17T12:42:24.321634", "to": "defender@q3mcco35auwcstmt.onion", "from": "driver@q3mcco35auwcstmt.onion", "body": "Error: The message is encrypted and cannot be decrypted.]"}, {"ts": "2021-08-17T12:42:57.553841", "to": "driver@q3mcco35auwcstmt.onion", "from": "defender@q3mcco35auwcstmt.onion", "body": "Error: The message is encrypted and cannot be decrypted.]"}, {"ts": "2021-08-17T12:49:59.445095", "to": "mango@q3mcco35auwcstmt.onion", "from": "buza@q3mcco35auwcstmt.onion", "body": "re"}, {"ts": "2021-08-17T12:51:29.293339", "to": "defender@q3mcco35auwcstmt.onion", "from": "driver@q3mcco35auwcstmt.onion", "body": "Error: The message is encrypted and cannot be decrypted.]"}, {"ts": "2021-08-17T13:21:39.283283", "to": "defender@q3mcco35auwcstmt.onion", "from": "driver@q3mcco35auwcstmt.onion", "body": "Error: The message is encrypted and cannot be decrypted.]"}, {"ts": "2021-08-17T13:24:07.634116", "to": "driver@q3mcco35auwcstmt.onion", "from": "defender@q3mcco35auwcstmt.onion", "body": "Error: The message is encrypted and cannot be decrypted.]"}, {"ts": "2021-08-17T13:29:48.977406", "to": "defender@q3mcco35auwcstmt.onion", "from": "driver@q3mcco35auwcstmt.onion", "body": "Error: The message is encrypted and cannot be decrypted.]"}, {"ts": "2021-08-17T13:31:02.545136", "to": "driver@q3mcco35auwcstmt.onion", "from": "defender@q3mcco35auwcstmt.onion", "body": "Error: The message is encrypted and cannot be decrypted.]"}, {"ts": "2021-08-17T13:31:39.228310", "to": "defender@q3mcco35auwcstmt.onion", "from": "driver@q3mcco35auwcstmt.onion", "body": "Error: The message is encrypted and cannot be decrypted.]"}, {"ts": "2021-08-17T13:32:02.526438", "to": "driver@q3mcco35auwcstmt.onion", "from": "defender@q3mcco35auwcstmt.onion", "body": "Error: The message is encrypted and cannot be decrypted.]"}, {"ts": "2021-08-17T13:32:55.670670", "to": "defender@q3mcco35auwcstmt.onion", "from": "driver@q3mcco35auwcstmt.onion", "body": "Error: The message is encrypted and cannot be decrypted.]"}, {"ts": "2021-08-17T13:34:02.149511", "to": "driver@q3mcco35auwcstmt.onion", "from": "defender@q3mcco35auwcstmt.onion", "body": "Error: The message is encrypted and cannot be decrypted.]"}, {"ts": "2021-08-17T13:49:54.963087", "to": "hors@q3mcco35auwcstmt.onion", "from": "buza@q3mcco35auwcstmt.onion", "body": "Hey"}, {"ts": "2021-08-17T14:46:14.875648", "to": "mango@q3mcco35auwcstmt.onion", "from": "buza@q3mcco35auwcstmt.onion", "body": "re"}, {"ts": "2021-08-17T14:58:47.025980", "to": "driver@q3mcco35auwcstmt.onion", "from": "defender@q3mcco35auwcstmt.onion", "body": "Error: The message is encrypted and cannot be decrypted.]"}, {"ts": "2021-08-17T14:59:48.582968", "to": "defender@q3mcco35auwcstmt.onion", "from": "driver@q3mcco35auwcstmt.onion", "body": "Error: The message is encrypted and cannot be decrypted.]"}, {"ts": "2021-08-17T15:15:00.493997", "to": "hof@q3mcco35auwcstmt.onion", "from": "defender@q3mcco35auwcstmt.onion", "body": "Error: The message is encrypted and cannot be decrypted.]"}, {"ts": "2021-08-17T15:15:13.006491", "to": "hof@q3mcco35auwcstmt.onion", "from": "defender@q3mcco35auwcstmt.onion", "body": "Error: The message is encrypted and cannot be decrypted.]"}, {"ts": "2021-08-17T15:15:27.345996", "to": "hof@q3mcco35auwcstmt.onion", "from": "defender@q3mcco35auwcstmt.onion", "body": "Error: The message is encrypted and cannot be decrypted.]"}, {"ts": "2021-08-17T15:15:42.938601", "to": "hof@q3mcco35auwcstmt.onion", "from": "defender@q3mcco35auwcstmt.onion", "body": "Error: The message is encrypted and cannot be decrypted.]"}, {"ts": "2021-08-17T15:16:27.146038", "to": "hof@q3mcco35auwcstmt.onion", "from": "defender@q3mcco35auwcstmt.onion", "body": "Error: The message is encrypted and cannot be decrypted.]"}, {"ts": "2021-08-17T15:24:44.966392", "to": "hof@q3mcco35auwcstmt.onion", "from": "defender@q3mcco35auwcstmt.onion", "body": "Error: The message is encrypted and cannot be decrypted.]"}, {"ts": "2021-08-17T15:33:37.234818", "to": "derekson@q3mcco35auwcstmt.onion", "from": "buza@q3mcco35auwcstmt.onion", "body": "+"}, {"ts": "2021-08-17T15:41:47.912130", "to": "revers@q3mcco35auwcstmt.onion", "from": "ford@q3mcco35auwcstmt.onion", "body": "Hey"}, {"ts": "2021-08-17T15:44:06.337357", "to": "defender@q3mcco35auwcstmt.onion", "from": "hof@q3mcco35auwcstmt.onion", "body": "Error: The message is encrypted and cannot be decrypted.]"}, {"ts": "2021-08-17T15:47:16.609761", "to": "defender@q3mcco35auwcstmt.onion", "from": "hof@q3mcco35auwcstmt.onion", "body": "Error: The message is encrypted and cannot be decrypted.]"}, {"ts": "2021-08-17T15:48:51.843741", "to": "hof@q3mcco35auwcstmt.onion", "from": "defender@q3mcco35auwcstmt.onion", "body": "Error: The message is encrypted and cannot be decrypted.]"}, {"ts": "2021-08-17T15:50:12.501466", "to": "defender@q3mcco35auwcstmt.onion", "from": "hof@q3mcco35auwcstmt.onion", "body": "Error: The message is encrypted and cannot be decrypted.]"}, {"ts": "2021-08-17T15:50:42.751879", "to": "hof@q3mcco35auwcstmt.onion", "from": "defender@q3mcco35auwcstmt.onion", "body": "Error: The message is encrypted and cannot be decrypted.]"}, {"ts": "2021-08-17T15:52:05.525941", "to": "defender@q3mcco35auwcstmt.onion", "from": "hof@q3mcco35auwcstmt.onion", "body": "Error: The message is encrypted and cannot be decrypted.]"}, {"ts": "2021-08-17T15:53:09.014151", "to": "hof@q3mcco35auwcstmt.onion", "from": "defender@q3mcco35auwcstmt.onion", "body": "Error: The message is encrypted and cannot be decrypted.]"}, {"ts": "2021-08-17T15:53:18.162126", "to": "hof@q3mcco35auwcstmt.onion", "from": "defender@q3mcco35auwcstmt.onion", "body": "Error: The message is encrypted and cannot be decrypted.]"}, {"ts": "2021-08-17T15:53:40.437274", "to": "hof@q3mcco35auwcstmt.onion", "from": "defender@q3mcco35auwcstmt.onion", "body": "Error: The message is encrypted and cannot be decrypted.]"}, {"ts": "2021-08-17T15:54:03.380834", "to": "defender@q3mcco35auwcstmt.onion", "from": "hof@q3mcco35auwcstmt.onion", "body": "Error: The message is encrypted and cannot be decrypted.]"}, {"ts": "2021-08-17T15:55:07.408069", "to": "defender@q3mcco35auwcstmt.onion", "from": "hof@q3mcco35auwcstmt.onion", "body": "Error: The message is encrypted and cannot be decrypted.]"}, {"ts": "2021-08-17T15:56:36.083099", "to": "defender@q3mcco35auwcstmt.onion", "from": "hof@q3mcco35auwcstmt.onion", "body": "Error: The message is encrypted and cannot be decrypted.]"}, {"ts": "2021-08-17T16:01:42.118486", "to": "hof@q3mcco35auwcstmt.onion", "from": "defender@q3mcco35auwcstmt.onion", "body": "Error: The message is encrypted and cannot be decrypted.]"}, {"ts": "2021-08-17T16:01:50.046357", "to": "defender@q3mcco35auwcstmt.onion", "from": "hof@q3mcco35auwcstmt.onion", "body": "Error: The message is encrypted and cannot be decrypted.]"}, {"ts": "2021-08-17T16:02:11.796510", "to": "hof@q3mcco35auwcstmt.onion", "from": "defender@q3mcco35auwcstmt.onion", "body": "Error: The message is encrypted and cannot be decrypted.]"}, {"ts": "2021-08-17T16:02:15.833531", "to": "defender@q3mcco35auwcstmt.onion", "from": "hof@q3mcco35auwcstmt.onion", "body": "Error: The message is encrypted and cannot be decrypted.]"}, {"ts": "2021-08-17T16:02:17.792659", "to": "hof@q3mcco35auwcstmt.onion", "from": "defender@q3mcco35auwcstmt.onion", "body": "Error: The message is encrypted and cannot be decrypted.]"}, {"ts": "2021-08-17T16:04:23.976607", "to": "defender@q3mcco35auwcstmt.onion", "from": "hof@q3mcco35auwcstmt.onion", "body": "Error: The message is encrypted and cannot be decrypted.]"}, {"ts": "2021-08-17T16:04:39.453646", "to": "hof@q3mcco35auwcstmt.onion", "from": "defender@q3mcco35auwcstmt.onion", "body": "Error: The message is encrypted and cannot be decrypted.]"}, {"ts": "2021-08-17T16:05:26.078924", "to": "defender@q3mcco35auwcstmt.onion", "from": "hof@q3mcco35auwcstmt.onion", "body": "Error: The message is encrypted and cannot be decrypted.]"}, {"ts": "2021-08-17T16:06:53.655806", "to": "defender@q3mcco35auwcstmt.onion", "from": "hof@q3mcco35auwcstmt.onion", "body": "Error: The message is encrypted and cannot be decrypted.]"}, {"ts": "2021-08-17T16:07:04.654648", "to": "defender@q3mcco35auwcstmt.onion", "from": "hof@q3mcco35auwcstmt.onion", "body": "Error: The message is encrypted and cannot be decrypted.]"}, {"ts": "2021-08-17T16:07:16.153295", "to": "hof@q3mcco35auwcstmt.onion", "from": "defender@q3mcco35auwcstmt.onion", "body": "Error: The message is encrypted and cannot be decrypted.]"}, {"ts": "2021-08-17T16:07:28.056452", "to": "defender@q3mcco35auwcstmt.onion", "from": "hof@q3mcco35auwcstmt.onion", "body": "Error: The message is encrypted and cannot be decrypted.]"}, {"ts": "2021-08-17T16:07:39.105072", "to": "hof@q3mcco35auwcstmt.onion", "from": "defender@q3mcco35auwcstmt.onion", "body": "Error: The message is encrypted and cannot be decrypted.]"}, {"ts": "2021-08-17T16:08:31.376016", "to": "defender@q3mcco35auwcstmt.onion", "from": "hof@q3mcco35auwcstmt.onion", "body": "Error: The message is encrypted and cannot be decrypted.]"}, {"ts": "2021-08-17T16:09:21.858310", "to": "hof@q3mcco35auwcstmt.onion", "from": "defender@q3mcco35auwcstmt.onion", "body": "Error: The message is encrypted and cannot be decrypted.]"}, {"ts": "2021-08-17T16:09:30.605122", "to": "defender@q3mcco35auwcstmt.onion", "from": "hof@q3mcco35auwcstmt.onion", "body": "Error: The message is encrypted and cannot be decrypted.]"}, {"ts": "2021-08-17T16:10:18.750168", "to": "defender@q3mcco35auwcstmt.onion", "from": "hof@q3mcco35auwcstmt.onion", "body": "Error: The message is encrypted and cannot be decrypted.]"}, {"ts": "2021-08-17T16:13:26.224877", "to": "hof@q3mcco35auwcstmt.onion", "from": "defender@q3mcco35auwcstmt.onion", "body": "Error: The message is encrypted and cannot be decrypted.]"}, {"ts": "2021-08-17T16:13:42.179909", "to": "defender@q3mcco35auwcstmt.onion", "from": "hof@q3mcco35auwcstmt.onion", "body": "Error: The message is encrypted and cannot be decrypted.]"}, {"ts": "2021-08-17T16:13:49.271749", "to": "defender@q3mcco35auwcstmt.onion", "from": "hof@q3mcco35auwcstmt.onion", "body": "Error: The message is encrypted and cannot be decrypted.]"}, {"ts": "2021-08-17T16:13:52.073033", "to": "hof@q3mcco35auwcstmt.onion", "from": "defender@q3mcco35auwcstmt.onion", "body": "Error: The message is encrypted and cannot be decrypted.]"}, {"ts": "2021-08-17T16:14:01.470031", "to": "defender@q3mcco35auwcstmt.onion", "from": "hof@q3mcco35auwcstmt.onion", "body": "Error: The message is encrypted and cannot be decrypted.]"}, {"ts": "2021-08-17T16:14:23.982372", "to": "hof@q3mcco35auwcstmt.onion", "from": "defender@q3mcco35auwcstmt.onion", "body": "Error: The message is encrypted and cannot be decrypted.]"}, {"ts": "2021-08-17T16:14:43.927430", "to": "defender@q3mcco35auwcstmt.onion", "from": "hof@q3mcco35auwcstmt.onion", "body": "Error: The message is encrypted and cannot be decrypted.]"}, {"ts": "2021-08-17T16:15:07.007992", "to": "hof@q3mcco35auwcstmt.onion", "from": "defender@q3mcco35auwcstmt.onion", "body": "Error: The message is encrypted and cannot be decrypted.]"}, {"ts": "2021-08-17T16:15:08.428407", "to": "defender@q3mcco35auwcstmt.onion", "from": "hof@q3mcco35auwcstmt.onion", "body": "Error: The message is encrypted and cannot be decrypted.]"}, {"ts": "2021-08-17T16:18:48.389489", "to": "defender@q3mcco35auwcstmt.onion", "from": "hof@q3mcco35auwcstmt.onion", "body": "Error: The message is encrypted and cannot be decrypted.]"}, {"ts": "2021-08-17T16:18:59.537847", "to": "defender@q3mcco35auwcstmt.onion", "from": "hof@q3mcco35auwcstmt.onion", "body": "Error: The message is encrypted and cannot be decrypted.]"}, {"ts": "2021-08-17T16:19:12.420400", "to": "viper@q3mcco35auwcstmt.onion", "from": "salamandra@q3mcco35auwcstmt.onion", "body": "<Stern>yes, you can rest for now and come back with renewed vigor, prove here to everyone what you are capable of"}, {"ts": "2021-08-17T16:19:31.514625", "to": "salamandra@q3mcco35auwcstmt.onion", "from": "viper@q3mcco35auwcstmt.onion", "body": ")"}, {"ts": "2021-08-17T16:19:58.702756", "to": "defender@q3mcco35auwcstmt.onion", "from": "hof@q3mcco35auwcstmt.onion", "body": "Error: The message is encrypted and cannot be decrypted.]"}, {"ts": "2021-08-17T16:20:59.296909", "to": "hof@q3mcco35auwcstmt.onion", "from": "defender@q3mcco35auwcstmt.onion", "body": "Error: The message is encrypted and cannot be decrypted.]"}, {"ts": "2021-08-17T16:21:10.395011", "to": "defender@q3mcco35auwcstmt.onion", "from": "hof@q3mcco35auwcstmt.onion", "body": "Error: The message is encrypted and cannot be decrypted.]"}, {"ts": "2021-08-17T16:21:13.577078", "to": "hof@q3mcco35auwcstmt.onion", "from": "defender@q3mcco35auwcstmt.onion", "body": "Error: The message is encrypted and cannot be decrypted.]"}, {"ts": "2021-08-17T16:21:30.809793", "to": "defender@q3mcco35auwcstmt.onion", "from": "hof@q3mcco35auwcstmt.onion", "body": "Error: The message is encrypted and cannot be decrypted.]"}, {"ts": "2021-08-17T16:22:03.002046", "to": "hof@q3mcco35auwcstmt.onion", "from": "defender@q3mcco35auwcstmt.onion", "body": "Error: The message is encrypted and cannot be decrypted.]"}, {"ts": "2021-08-17T16:22:50.765743", "to": "defender@q3mcco35auwcstmt.onion", "from": "hof@q3mcco35auwcstmt.onion", "body": "Error: The message is encrypted and cannot be decrypted.]"}, {"ts": "2021-08-17T16:23:57.948059", "to": "hof@q3mcco35auwcstmt.onion", "from": "defender@q3mcco35auwcstmt.onion", "body": "Error: The message is encrypted and cannot be decrypted.]"}, {"ts": "2021-08-17T16:24:11.209168", "to": "defender@q3mcco35auwcstmt.onion", "from": "hof@q3mcco35auwcstmt.onion", "body": "Error: The message is encrypted and cannot be decrypted.]"}, {"ts": "2021-08-17T16:24:25.104655", "to": "defender@q3mcco35auwcstmt.onion", "from": "hof@q3mcco35auwcstmt.onion", "body": "Error: The message is encrypted and cannot be decrypted.]"}, {"ts": "2021-08-17T16:24:57.946627", "to": "defender@q3mcco35auwcstmt.onion", "from": "hof@q3mcco35auwcstmt.onion", "body": "Error: The message is encrypted and cannot be decrypted.]"}, {"ts": "2021-08-17T16:25:05.981357", "to": "hof@q3mcco35auwcstmt.onion", "from": "defender@q3mcco35auwcstmt.onion", "body": "Error: The message is encrypted and cannot be decrypted.]"}, {"ts": "2021-08-17T16:25:17.353716", "to": "defender@q3mcco35auwcstmt.onion", "from": "hof@q3mcco35auwcstmt.onion", "body": "Error: The message is encrypted and cannot be decrypted.]"}, {"ts": "2021-08-17T16:25:27.952174", "to": "hof@q3mcco35auwcstmt.onion", "from": "defender@q3mcco35auwcstmt.onion", "body": "Error: The message is encrypted and cannot be decrypted.]"}, {"ts": "2021-08-17T16:25:44.630613", "to": "defender@q3mcco35auwcstmt.onion", "from": "hof@q3mcco35auwcstmt.onion", "body": "Error: The message is encrypted and cannot be decrypted.]"}, {"ts": "2021-08-17T16:26:03.768111", "to": "hof@q3mcco35auwcstmt.onion", "from": "defender@q3mcco35auwcstmt.onion", "body": "Error: The message is encrypted and cannot be decrypted.]"}, {"ts": "2021-08-17T16:26:30.894975", "to": "defender@q3mcco35auwcstmt.onion", "from": "hof@q3mcco35auwcstmt.onion", "body": "Error: The message is encrypted and cannot be decrypted.]"}, {"ts": "2021-08-17T16:26:41.305618", "to": "hof@q3mcco35auwcstmt.onion", "from": "defender@q3mcco35auwcstmt.onion", "body": "Error: The message is encrypted and cannot be decrypted.]"}, {"ts": "2021-08-17T16:26:43.666091", "to": "defender@q3mcco35auwcstmt.onion", "from": "hof@q3mcco35auwcstmt.onion", "body": "Error: The message is encrypted and cannot be decrypted.]"}, {"ts": "2021-08-17T16:26:53.940183", "to": "hof@q3mcco35auwcstmt.onion", "from": "defender@q3mcco35auwcstmt.onion", "body": "Error: The message is encrypted and cannot be decrypted.]"}, {"ts": "2021-08-17T16:27:28.390254", "to": "defender@q3mcco35auwcstmt.onion", "from": "hof@q3mcco35auwcstmt.onion", "body": "Error: The message is encrypted and cannot be decrypted.]"}, {"ts": "2021-08-17T16:29:07.702242", "to": "hof@q3mcco35auwcstmt.onion", "from": "defender@q3mcco35auwcstmt.onion", "body": "Error: The message is encrypted and cannot be decrypted.]"}, {"ts": "2021-08-17T16:29:10.358594", "to": "defender@q3mcco35auwcstmt.onion", "from": "hof@q3mcco35auwcstmt.onion", "body": "Error: The message is encrypted and cannot be decrypted.]"}, {"ts": "2021-08-17T16:29:23.818588", "to": "hof@q3mcco35auwcstmt.onion", "from": "defender@q3mcco35auwcstmt.onion", "body": "Error: The message is encrypted and cannot be decrypted.]"}, {"ts": "2021-08-17T16:30:56.321445", "to": "stern@q3mcco35auwcstmt.onion", "from": "salamandra@q3mcco35auwcstmt.onion", "body": "agreed!"}, {"ts": "2021-08-17T16:35:10.008945", "to": "hof@q3mcco35auwcstmt.onion", "from": "defender@q3mcco35auwcstmt.onion", "body": "Error: The message is encrypted and cannot be decrypted.]"}, {"ts": "2021-08-17T16:36:44.872057", "to": "defender@q3mcco35auwcstmt.onion", "from": "hof@q3mcco35auwcstmt.onion", "body": "Error: The message is encrypted and cannot be decrypted.]"}, {"ts": "2021-08-17T16:36:51.533966", "to": "hof@q3mcco35auwcstmt.onion", "from": "defender@q3mcco35auwcstmt.onion", "body": "Error: The message is encrypted and cannot be decrypted.]"}, {"ts": "2021-08-17T16:36:52.549184", "to": "defender@q3mcco35auwcstmt.onion", "from": "hof@q3mcco35auwcstmt.onion", "body": "Error: The message is encrypted and cannot be decrypted.]"}, {"ts": "2021-08-17T16:43:42.710410", "to": "hof@q3mcco35auwcstmt.onion", "from": "defender@q3mcco35auwcstmt.onion", "body": "Error: The message is encrypted and cannot be decrypted.]"}, {"ts": "2021-08-17T16:44:21.211417", "to": "defender@q3mcco35auwcstmt.onion", "from": "hof@q3mcco35auwcstmt.onion", "body": "Error: The message is encrypted and cannot be decrypted.]"}, {"ts": "2021-08-17T16:44:53.433456", "to": "hof@q3mcco35auwcstmt.onion", "from": "defender@q3mcco35auwcstmt.onion", "body": "Error: The message is encrypted and cannot be decrypted.]"}, {"ts": "2021-08-17T16:48:54.738812", "to": "stern@q3mcco35auwcstmt.onion", "from": "mango@q3mcco35auwcstmt.onion", "body": "zp distributed everything except the green, he is on vacation, I will throw it in as soon as possible"}, {"ts": "2021-08-17T16:53:02.701449", "to": "hof@q3mcco35auwcstmt.onion", "from": "defender@q3mcco35auwcstmt.onion", "body": "Error: The message is encrypted and cannot be decrypted.]"}, {"ts": "2021-08-17T16:53:52.028352", "to": "defender@q3mcco35auwcstmt.onion", "from": "hof@q3mcco35auwcstmt.onion", "body": "Error: The message is encrypted and cannot be decrypted.]"}, {"ts": "2021-08-17T16:54:30.849511", "to": "hof@q3mcco35auwcstmt.onion", "from": "defender@q3mcco35auwcstmt.onion", "body": "Error: The message is encrypted and cannot be decrypted.]"}, {"ts": "2021-08-17T16:54:51.171226", "to": "defender@q3mcco35auwcstmt.onion", "from": "hof@q3mcco35auwcstmt.onion", "body": "Error: The message is encrypted and cannot be decrypted.]"}, {"ts": "2021-08-17T16:58:35.890569", "to": "defender@q3mcco35auwcstmt.onion", "from": "hof@q3mcco35auwcstmt.onion", "body": "Error: The message is encrypted and cannot be decrypted.]"}, {"ts": "2021-08-17T16:58:52.172896", "to": "defender@q3mcco35auwcstmt.onion", "from": "hof@q3mcco35auwcstmt.onion", "body": "Error: The message is encrypted and cannot be decrypted.]"}, {"ts": "2021-08-17T17:07:03.437553", "to": "hof@q3mcco35auwcstmt.onion", "from": "defender@q3mcco35auwcstmt.onion", "body": "Error: The message is encrypted and cannot be decrypted.]"}, {"ts": "2021-08-17T17:08:30.047178", "to": "defender@q3mcco35auwcstmt.onion", "from": "hof@q3mcco35auwcstmt.onion", "body": "Error: The message is encrypted and cannot be decrypted.]"}, {"ts": "2021-08-17T17:08:45.895071", "to": "hof@q3mcco35auwcstmt.onion", "from": "defender@q3mcco35auwcstmt.onion", "body": "Error: The message is encrypted and cannot be decrypted.]"}, {"ts": "2021-08-17T17:54:13.785994", "to": "stern@q3mcco35auwcstmt.onion", "from": "tom@q3mcco35auwcstmt.onion", "body": "hi will you write"}, {"ts": "2021-08-17T18:26:52.203047", "to": "kramer@q3mcco35auwcstmt.onion", "from": "grant@q3mcco35auwcstmt.onion", "body": "I made an appointment for tomorrow"}, {"ts": "2021-08-17T18:26:52.211785", "to": "kramer@q3mcco35auwcstmt.onion", "from": "grant@q3mcco35auwcstmt.onion", "body": "get ready"}, {"ts": "2021-08-17T18:26:52.402380", "to": "kramer@q3mcco35auwcstmt.onion", "from": "grant@q3mcco35auwcstmt.onion", "body": "the file will be good"}, {"ts": "2021-08-17T18:30:14.670032", "to": "cherry@q3mcco35auwcstmt.onion", "from": "zevs@q3mcco35auwcstmt.onion", "body": "the toad disconnected"}, {"ts": "2021-08-17T18:30:23.625470", "to": "cherry@q3mcco35auwcstmt.onion", "from": "zevs@q3mcco35auwcstmt.onion", "body": "Yes, I say that the Spaniard was deanommiled by the Feds"}, {"ts": "2021-08-17T18:34:06.901592", "to": "zevs@q3mcco35auwcstmt.onion", "from": "cherry@q3mcco35auwcstmt.onion", "body": "the toad disconnected"}, {"ts": "2021-08-17T18:34:06.912295", "to": "zevs@q3mcco35auwcstmt.onion", "from": "cherry@q3mcco35auwcstmt.onion", "body": "Yes, I say that the Spaniard was deanommiled by the Feds"}, {"ts": "2021-08-17T19:09:01.441462", "to": "mango@q3mcco35auwcstmt.onion", "from": "bentley@q3mcco35auwcstmt.onion", "body": "Ready report on crypts for 16.08"}, {"ts": "2021-08-17T19:09:11.441150", "to": "mango@q3mcco35auwcstmt.onion", "from": "bentley@q3mcco35auwcstmt.onion", "body": "Project Leo - 6 crypts BC group 5: 6 crypts build machine group 19: 5 crypts build machine Trick: 6 dll: 6 sam 3 exe: 3 sam Troika: sam Shelcode: build machine"}, {"ts": "2021-08-17T19:21:31.885702", "to": "driver@q3mcco35auwcstmt.onion", "from": "zulas@q3mcco35auwcstmt.onion", "body": "Hey"}, {"ts": "2021-08-17T20:17:35.278967", "to": "mango@q3mcco35auwcstmt.onion", "from": "bentley@q3mcco35auwcstmt.onion", "body": "Ready report on crypts for 16.08"}, {"ts": "2021-08-17T20:17:35.279709", "to": "mango@q3mcco35auwcstmt.onion", "from": "bentley@q3mcco35auwcstmt.onion", "body": "Project Leo - 6 crypts BC group 5: 6 crypts build machine group 19: 5 crypts build machine Trick: 6 dll: 6 sam 3 exe: 3 sam Troika: sam Shelcode: build machine"}]