[{"ts": "2021-04-04T07:40:54.548881", "to": "defender@q3mcco35auwcstmt.onion", "from": "veron@q3mcco35auwcstmt.onion", "body": "Error: The message is encrypted and cannot be decrypted.]"}, {"ts": "2021-04-04T10:05:21.814293", "to": "miguel@q3mcco35auwcstmt.onion", "from": "tiktak@q3mcco35auwcstmt.onion", "body": "hi bro here?"}, {"ts": "2021-04-04T17:17:13.230898", "to": "stern@q3mcco35auwcstmt.onion", "from": "mavemat@q3mcco35auwcstmt.onion", "body": "will you throw a zp?"}, {"ts": "2021-04-04T19:46:42.633917", "to": "revers@q3mcco35auwcstmt.onion", "from": "johnyboy77@q3mcco35auwcstmt.onion", "body": "private"}, {"ts": "2021-04-04T20:05:20.802394", "to": "grajdanin@q3mcco35auwcstmt.onion", "from": "modnik@q3mcco35auwcstmt.onion", "body": "https://privnote.com/gmm61ejt#JLSN6aBbc"}]